autctapi/__init__.py
autctapi/wsapi.py
autctapi-0.0.4.dist-info/METADATA
autctapi-0.0.4.dist-info/WHEEL
autctapi-0.0.4.dist-info/top_level.txt
autctapi-0.0.4.dist-info/RECORD
