Metadata-Version: 2.1
Name: autctapi
Version: 0.0.4
Summary: Autct websocket API client in Python
Author-email: AdamISZ <no@example.com>
Project-URL: repository, https://github.com/AdamISZ/autct-api.git
Classifier: Programming Language :: Python :: 3
Classifier: Operating System :: OS Independent
Requires-Python: >=3.8
Requires-Dist: websockets
